spacy_alignments/__init__.py
spacy_alignments/tokenizations.cpython-310-aarch64-linux-gnu.so
spacy_alignments/py.typed
spacy_alignments/__init__.pyi
spacy_alignments/tests/__init__.py
spacy_alignments/tests/test_main.py
spacy_alignments.libs/libgcc_s-7393e603.so.1
spacy_alignments-0.9.2.dist-info/RECORD
spacy_alignments-0.9.2.dist-info/WHEEL
spacy_alignments-0.9.2.dist-info/METADATA
spacy_alignments-0.9.2.dist-info/top_level.txt
spacy_alignments-0.9.2.dist-info/licenses/LICENSE
